MANIFEST.in
README.md
setup.py
aether_chart_generator/args.py
aether_chart_generator/generator.py
aether_chart_generator.egg-info/PKG-INFO
aether_chart_generator.egg-info/SOURCES.txt
aether_chart_generator.egg-info/dependency_links.txt
aether_chart_generator.egg-info/entry_points.txt
aether_chart_generator.egg-info/not-zip-safe
aether_chart_generator.egg-info/requires.txt
aether_chart_generator.egg-info/top_level.txt
aether_chart_generator/templates/Chart.tmpl.yaml
aether_chart_generator/templates/NOTES.tmpl.txt
aether_chart_generator/templates/_helpers.tmpl.tpl
aether_chart_generator/templates/deployment.tmpl.yaml
aether_chart_generator/templates/ingress.tmpl.yaml
aether_chart_generator/templates/init-config-map.tmpl.yaml
aether_chart_generator/templates/nginx-config-map.tmpl.yaml
aether_chart_generator/templates/service.tmpl.yaml